tigers/__init__.py
tigers/api.py
tigers/config/__init__.py
tigers/config/info.py
tigers-0.0.1.dist-info/METADATA
tigers-0.0.1.dist-info/WHEEL
tigers-0.0.1.dist-info/top_level.txt
tigers-0.0.1.dist-info/RECORD
